trieste/VERSION
trieste/__init__.py
trieste/ask_tell_optimization.py
trieste/bayesian_optimizer.py
trieste/data.py
trieste/logging.py
trieste/observer.py
trieste/py.typed
trieste/space.py
trieste/types.py
trieste/version.py
trieste/acquisition/__init__.py
trieste/acquisition/combination.py
trieste/acquisition/interface.py
trieste/acquisition/optimizer.py
trieste/acquisition/rule.py
trieste/acquisition/sampler.py
trieste/acquisition/utils.py
trieste/acquisition/function/__init__.py
trieste/acquisition/function/active_learning.py
trieste/acquisition/function/continuous_thompson_sampling.py
trieste/acquisition/function/entropy.py
trieste/acquisition/function/function.py
trieste/acquisition/function/greedy_batch.py
trieste/acquisition/function/multi_objective.py
trieste/acquisition/function/utils.py
trieste/acquisition/multi_objective/__init__.py
trieste/acquisition/multi_objective/dominance.py
trieste/acquisition/multi_objective/pareto.py
trieste/acquisition/multi_objective/partition.py
trieste/experimental/__init__.py
trieste/experimental/plotting/__init__.py
trieste/experimental/plotting/inequality_constraints.py
trieste/experimental/plotting/plotting.py
trieste/experimental/plotting/plotting_plotly.py
trieste/models/__init__.py
trieste/models/interfaces.py
trieste/models/optimizer.py
trieste/models/utils.py
trieste/models/gpflow/__init__.py
trieste/models/gpflow/builders.py
trieste/models/gpflow/inducing_point_selectors.py
trieste/models/gpflow/interface.py
trieste/models/gpflow/models.py
trieste/models/gpflow/optimizer.py
trieste/models/gpflow/sampler.py
trieste/models/gpflow/utils.py
trieste/models/gpflux/__init__.py
trieste/models/gpflux/builders.py
trieste/models/gpflux/interface.py
trieste/models/gpflux/models.py
trieste/models/gpflux/sampler.py
trieste/models/keras/__init__.py
trieste/models/keras/architectures.py
trieste/models/keras/builders.py
trieste/models/keras/interface.py
trieste/models/keras/models.py
trieste/models/keras/sampler.py
trieste-4.5.1.dist-info/licenses/LICENSE
trieste-4.5.1.dist-info/METADATA
trieste-4.5.1.dist-info/WHEEL
trieste-4.5.1.dist-info/top_level.txt
trieste-4.5.1.dist-info/RECORD
