Metadata-Version: 2.4
Name: trieste
Version: 4.5.1
Summary: A Bayesian optimization research toolbox built on TensorFlow
Home-page: https://github.com/secondmind-labs/trieste
Author: The Trieste contributors
Author-email: labs@secondmind.ai
Classifier: Programming Language :: Python :: 3.9
Classifier: License :: OSI Approved :: Apache Software License
Classifier: Operating System :: OS Independent
Requires-Python: ~=3.9
License-File: LICENSE
Requires-Dist: absl-py
Requires-Dist: dill<0.3.6
Requires-Dist: gpflow>=2.9.2
Requires-Dist: gpflux>=0.4.4
Requires-Dist: numpy
Requires-Dist: tensorflow<2.17,>=2.5; platform_system != "Darwin" or platform_machine != "arm64"
Requires-Dist: tensorflow-macos<2.17,>=2.5; platform_system == "Darwin" and platform_machine == "arm64"
Requires-Dist: tensorflow-probability<0.25,>=0.13
Requires-Dist: greenlet>=1.1.0
Provides-Extra: plotting
Requires-Dist: seaborn; extra == "plotting"
Requires-Dist: plotly; extra == "plotting"
Requires-Dist: imageio; extra == "plotting"
Provides-Extra: qhsri
Requires-Dist: pymoo; extra == "qhsri"
Requires-Dist: cvxpy; extra == "qhsri"
Dynamic: author
Dynamic: author-email
Dynamic: classifier
Dynamic: description
Dynamic: description-content-type
Dynamic: home-page
Dynamic: license-file
Dynamic: provides-extra
Dynamic: requires-dist
Dynamic: requires-python
Dynamic: summary
